youtube_dl_gui_server/__init__.py
youtube_dl_gui_server/__version__.py
youtube_dl_gui_server/dfn_error.py
youtube_dl_gui_server/main.py
youtube_dl_gui_server/routing.py
youtube_dl_gui_server/static/css/bootstrap-grid.css
youtube_dl_gui_server/static/css/bootstrap-grid.css.map
youtube_dl_gui_server/static/css/bootstrap-grid.min.css
youtube_dl_gui_server/static/css/bootstrap-grid.min.css.map
youtube_dl_gui_server/static/css/bootstrap-grid.rtl.css
youtube_dl_gui_server/static/css/bootstrap-grid.rtl.css.map
youtube_dl_gui_server/static/css/bootstrap-grid.rtl.min.css
youtube_dl_gui_server/static/css/bootstrap-grid.rtl.min.css.map
youtube_dl_gui_server/static/css/bootstrap-reboot.css
youtube_dl_gui_server/static/css/bootstrap-reboot.css.map
youtube_dl_gui_server/static/css/bootstrap-reboot.min.css
youtube_dl_gui_server/static/css/bootstrap-reboot.min.css.map
youtube_dl_gui_server/static/css/bootstrap-reboot.rtl.css
youtube_dl_gui_server/static/css/bootstrap-reboot.rtl.css.map
youtube_dl_gui_server/static/css/bootstrap-reboot.rtl.min.css
youtube_dl_gui_server/static/css/bootstrap-reboot.rtl.min.css.map
youtube_dl_gui_server/static/css/bootstrap-utilities.css
youtube_dl_gui_server/static/css/bootstrap-utilities.css.map
youtube_dl_gui_server/static/css/bootstrap-utilities.min.css
youtube_dl_gui_server/static/css/bootstrap-utilities.min.css.map
youtube_dl_gui_server/static/css/bootstrap-utilities.rtl.css
youtube_dl_gui_server/static/css/bootstrap-utilities.rtl.css.map
youtube_dl_gui_server/static/css/bootstrap-utilities.rtl.min.css
youtube_dl_gui_server/static/css/bootstrap-utilities.rtl.min.css.map
youtube_dl_gui_server/static/css/bootstrap.css
youtube_dl_gui_server/static/css/bootstrap.css.map
youtube_dl_gui_server/static/css/bootstrap.min.css
youtube_dl_gui_server/static/css/bootstrap.min.css.map
youtube_dl_gui_server/static/css/bootstrap.rtl.css
youtube_dl_gui_server/static/css/bootstrap.rtl.css.map
youtube_dl_gui_server/static/css/bootstrap.rtl.min.css
youtube_dl_gui_server-0.0.1.dist-info/LICENSE
youtube_dl_gui_server-0.0.1.dist-info/METADATA
youtube_dl_gui_server-0.0.1.dist-info/WHEEL
youtube_dl_gui_server-0.0.1.dist-info/entry_points.txt
youtube_dl_gui_server-0.0.1.dist-info/top_level.txt
youtube_dl_gui_server-0.0.1.dist-info/RECORD
