Metadata-Version: 2.1
Name: youtube-dl-gui-server
Version: 0.0.1
Summary: GUI server for youtube-dl
Home-page: https://github.com/kazuto28/youtube-dl-server
Author: Kondo Kazuto
Author-email: mountaindull@gmail.com
License: MIT
Platform: UNKNOWN
Classifier: Environment :: Console
Classifier: License :: OSI Approved :: MIT License
Classifier: Natural Language :: Japanese
Classifier: Natural Language :: English
Classifier: Operating System :: Unix
Classifier: Programming Language :: Python :: 3 :: Only
License-File: LICENSE
Requires-Dist: click (==8.0.1)
Requires-Dist: Flask (==2.0.1)
Requires-Dist: itsdangerous (==2.0.1)
Requires-Dist: Jinja2 (==3.0.1)
Requires-Dist: MarkupSafe (==2.0.1)
Requires-Dist: Werkzeug (==2.0.1)
Requires-Dist: youtube-dl (==2021.6.6)
